pybet/__init__.py
pybet/bets/__init__.py
pybet/bets/accumulator.py
pybet/bets/bet.py
pybet/bets/double.py
pybet/bets/py.typed
pybet/bets/treble.py
pybet/market.py
pybet/odds.py
pybet/staking/__init__.py
pybet/staking/kelly.py
pybet-0.8.4.dist-info/LICENSE
pybet-0.8.4.dist-info/METADATA
pybet-0.8.4.dist-info/WHEEL
pybet-0.8.4.dist-info/RECORD
