Metadata-Version: 2.1
Name: pybet
Version: 0.8.4
Summary: A library of betting utilities to assist with calculation of bets, stakes and markets
Home-page: https://github.com/peaky76/pybet
License: GPL-3.0-only
Keywords: betting,gambling
Author: Robert Peacock
Author-email: robertjamespeacock@gmail.com
Requires-Python: >=3.11,<4.0
Classifier: License :: OSI Approved :: GNU General Public License v3 (GPLv3)
Classifier: Operating System :: OS Independent
Classifier: Programming Language :: Python :: 3
Classifier: Programming Language :: Python :: 3.11
Requires-Dist: peak-utility (>=0.7.0,<0.8.0)
Project-URL: Documentation, https://pybet.readthedocs.io/
Project-URL: Repository, https://github.com/peaky76/pybet
